networkutil/__init__.py
networkutil/_metadata.py
networkutil/addressing.py
networkutil/device_config.py
networkutil/endpoint_config.py
networkutil/ftp_helper.py
networkutil/ftp_server.py
networkutil/http_download.py
networkutil/interfaces.py
networkutil/jumpbox.py
networkutil/port_forward.py
networkutil/scp_client.py
networkutil/service_check.py
networkutil/sftp.py
networkutil/telnet.py
networkutil/validation.py
networkutil/web_socket.py
networkutil/device/__init__.py
networkutil/device/_constants.py
networkutil/device/config.py
networkutil/device/devices.py
networkutil/gui/__init__.py
networkutil/gui/api_frame.py
networkutil/gui/api_window.py
networkutil/gui/endpoint_config_launcher_frame.py
networkutil/gui/endpoint_config_launcher_window.py
networkutil/gui/endpoint_frame.py
networkutil/gui/endpoint_window.py
networkutil/gui/environments_frame.py
networkutil/gui/environments_window.py
networkutil/gui/ip_widget.py
networkutil/gui/ipv4_widget.py
networkutil/gui/ipv6_widget.py
networkutil/gui/jumpbox_frame.py
networkutil/gui/pickler_frame.py
networkutil/gui/run_networkutil_gui.py
networkutil/mail/__init__.py
networkutil/mail/outlook.py
networkutil/mail/smtp.py
networkutil/resources/__init__.py
networkutil/resources/mac_port_forward/__init__.py
networkutil/resources/schema/__init__.py
networkutil/resources/schema/devices.json
networkutil/resources/schema/endpoints.json
networkutil/resources/schema/jumpbox.json
networkutil/resources/schema/ssl.json
networkutil/resources/templates/__init__.py
networkutil/resources/templates/api_layout.json
networkutil/resources/templates/endpoint_launcher_layout.json
networkutil/resources/templates/endpoint_layout.json
networkutil/resources/templates/endpoints.json
networkutil/resources/templates/environments_layout.json
networkutil/resources/templates/jumpbox.json
networkutil/resources/templates/ssl.json
networkutil/sniffer/__init__.py
networkutil/sniffer/_constants.py
networkutil/sniffer/helpers.py
networkutil-1.19.12.dist-info/LICENSE.txt
networkutil-1.19.12.dist-info/METADATA
networkutil-1.19.12.dist-info/WHEEL
networkutil-1.19.12.dist-info/entry_points.txt
networkutil-1.19.12.dist-info/top_level.txt
networkutil-1.19.12.dist-info/RECORD
