Metadata-Version: 2.1
Name: networkutil
Version: 1.19.12
Summary: A collection of networking utilities.
Home-page: https://bitbucket.org/davisowb/owbd-python-module-template.git
Author: Oli Davis & Hywel Thomas
Author-email: oli.davis@me.com, hywel.thomas@mac.com
License: MIT
Download-URL: https://bitbucket.org/davisowb/owbd-python-module-template.git/get/1.19.12.tar
Keywords: networkutil
Platform: UNKNOWN
Classifier: Development Status :: 3 - Alpha
Classifier: Intended Audience :: Developers
Classifier: License :: OSI Approved :: MIT License
Classifier: Programming Language :: Python :: 2
Classifier: Programming Language :: Python :: 2.7
Classifier: Programming Language :: Python :: 3
Classifier: Programming Language :: Python :: 3.6
Classifier: Topic :: Utilities
License-File: LICENSE.txt
Requires-Dist: attrs (>=17.3.0)
Requires-Dist: requests (>=2.7.0)
Requires-Dist: pyftpdlib (==1.5.4)
Requires-Dist: scp (>=0.10.2)
Requires-Dist: paramiko (>=2.0.2)
Requires-Dist: netifaces (>=0.10.5)
Requires-Dist: cryptography (>=2.2.1)
Requires-Dist: better-exceptions (>=0.1.6)
Requires-Dist: logging-helper (>=1.5.0)
Requires-Dist: conversionutil (>=1.0.0)
Requires-Dist: classutils (>=1.15.1)
Requires-Dist: configurationutil (>=3.0.2)
Requires-Dist: stateutil (>=1.0.8)
Requires-Dist: uiutil (>=1.16.1)
Requires-Dist: timingsutil (>=1.2.0)
Requires-Dist: pydnserver (>=2.2.8)
Requires-Dist: websocket-client (==0.52.0)
Requires-Dist: ipaddress (>=1.0.19)
Requires-Dist: future (>=0.16.0)
Requires-Dist: fdutil (>=1.7.8)
Provides-Extra: sniffer
Requires-Dist: pcapy (>=0.11.1) ; extra == 'sniffer'
Provides-Extra: test
